qoin/__init__.py
qoin/qrng.py
qoin-1.0.7.dist-info/LICENSE
qoin-1.0.7.dist-info/METADATA
qoin-1.0.7.dist-info/WHEEL
qoin-1.0.7.dist-info/top_level.txt
qoin-1.0.7.dist-info/RECORD
