Metadata-Version: 2.1
Name: qoin
Version: 1.0.7
Summary: Quantum Random Number Generator.
Author: Amir Ali Malekani Nezhad
Author-email: Amir Ali Malekani Nezhad <amiralimlk07@gmail.com>
License: GNU GENERAL PUBLIC LICENSE
Project-URL: Homepage, https://github.com/ACE07-Sev/Qoin
Keywords: quantum computing,random,random generator
Classifier: License :: OSI Approved :: GNU General Public License v3 (GPLv3)
Classifier: Programming Language :: Python
Classifier: Programming Language :: Python :: 3
Requires-Python: >=3.9
License-File: LICENSE
Requires-Dist: numpy
Requires-Dist: qiskit
Provides-Extra: dev
Requires-Dist: black ; extra == 'dev'
Requires-Dist: bumpver ; extra == 'dev'
Requires-Dist: isort ; extra == 'dev'
Requires-Dist: pip-tools ; extra == 'dev'
Requires-Dist: pytest ; extra == 'dev'
